{"trial_id": "1", "hyperparameters": {"space": [{"class_name": "Int", "config": {"name": "neurons", "default": null, "conditions": [], "min_value": 20, "max_value": 150, "step": 10, "sampling": "linear"}}, {"class_name": "Choice", "config": {"name": "optimizer", "default": "adam", "conditions": [], "values": ["adam", "sgd", "adagrad", "adamw"], "ordered": false}}, {"class_name": "Choice", "config": {"name": "loss", "default": "mse", "conditions": [], "values": ["mse", "mae", "msle", "rmse"], "ordered": false}}, {"class_name": "Choice", "config": {"name": "activation", "default": "relu", "conditions": [], "values": ["relu", "tanh", "sigmoid", "softmax"], "ordered": false}}], "values": {"neurons": 30, "optimizer": "sgd", "loss": "mse", "activation": "relu"}}, "metrics": {"metrics": {"loss": {"direction": "min", "observations": [{"value": [0.021132875233888626], "step": 1}]}, "mse": {"direction": "min", "observations": [{"value": [0.016681043431162834], "step": 1}]}, "val_loss": {"direction": "min", "observations": [{"value": [0.020203636959195137], "step": 1}]}, "val_mse": {"direction": "min", "observations": [{"value": [0.014995977282524109], "step": 1}]}}}, "score": 0.020203636959195137, "best_step": 1, "status": "COMPLETED", "message": null}